qssh/__init__.py
qssh/cli.py
qssh/connector.py
qssh/py.typed
qssh/session.py
qssh-0.2.5.dist-info/licenses/LICENSE
qssh-0.2.5.dist-info/METADATA
qssh-0.2.5.dist-info/WHEEL
qssh-0.2.5.dist-info/entry_points.txt
qssh-0.2.5.dist-info/top_level.txt
qssh-0.2.5.dist-info/RECORD
