Metadata-Version: 2.4
Name: qssh
Version: 0.2.5
Summary: Quick SSH session manager - save your VM credentials and connect with a single command
Author: joan-code6
License-Expression: MIT
Project-URL: Homepage, https://github.com/joan-code6/qssh
Project-URL: Repository, https://github.com/joan-code6/qssh
Project-URL: Issues, https://github.com/joan-code6/qssh/issues
Keywords: ssh,session,manager,vm,cli,terminal
Classifier: Development Status :: 4 - Beta
Classifier: Environment :: Console
Classifier: Intended Audience :: Developers
Classifier: Intended Audience :: System Administrators
Classifier: Operating System :: OS Independent
Classifier: Programming Language :: Python :: 3
Classifier: Programming Language :: Python :: 3.8
Classifier: Programming Language :: Python :: 3.9
Classifier: Programming Language :: Python :: 3.10
Classifier: Programming Language :: Python :: 3.11
Classifier: Programming Language :: Python :: 3.12
Classifier: Topic :: System :: Networking
Classifier: Topic :: Utilities
Requires-Python: >=3.8
License-File: LICENSE
Requires-Dist: click>=8.0.0
Requires-Dist: rich>=13.0.0
Requires-Dist: pyyaml>=6.0
Requires-Dist: paramiko>=3.0.0
Dynamic: license-file
